setup.cfg
setup.py
picsort/__init__.py
picsort/sort.py
picsort.egg-info/PKG-INFO
picsort.egg-info/SOURCES.txt
picsort.egg-info/dependency_links.txt
picsort.egg-info/entry_points.txt
picsort.egg-info/requires.txt
picsort.egg-info/top_level.txt