Metadata-Version: 1.0
Name: picsort
Version: 1.0
Summary: Safely de-duplicate and sort files
Home-page: https://github.com/jhford/picsort
Author: John H. Ford
Author-email: john+picsort.johnford@org
License: GPLv2
Keywords: photography raw nef cr2
Platform: UNKNOWN
